json_lisfy/__init__.py
json_lisfy/__main__.py
json_lisfy/reader.py
json_lisfy/rep.py
json_lisfy/subr/__init__.py
json_lisfy/subr/itertools.py
json_lisfy/subr/reader.py
json_lisfy/subr/subr.py
json_lisfy/types.py
json_lisfy-0.1.0.dist-info/LICENSE
json_lisfy-0.1.0.dist-info/METADATA
json_lisfy-0.1.0.dist-info/WHEEL
json_lisfy-0.1.0.dist-info/entry_points.txt
json_lisfy-0.1.0.dist-info/RECORD
