Metadata-Version: 2.1
Name: json-lisfy
Version: 0.1.0
Summary: 
License: Apache-2.0
Author: Naoya Yamashita
Author-email: conao3@gmail.com
Requires-Python: >=3.11,<4.0
Classifier: License :: OSI Approved :: Apache Software License
Classifier: Programming Language :: Python :: 3
Classifier: Programming Language :: Python :: 3.11
Requires-Dist: more-itertools (>=9.1.0,<10.0.0)
Requires-Dist: pydantic (>=1.10.9,<2.0.0)
